LAB1/bound_flasher.v
module bound_flasher (
  output reg [15:0] lamp,
  input  wire       clk,
  input  wire       rst_n,
  input  wire       flick
);
  parameter INIT = 4'd0;
  parameter S1   = 4'd1;
  parameter S2   = 4'd2;
  parameter S3   = 4'd3;
  parameter S3K  = 4'd4;
  parameter S4   = 4'd5;
  parameter S5   = 4'd6;
  parameter S5K  = 4'd7;
  parameter S6   = 4'd8;

  reg [3:0]  state, next_state;
  reg [15:0] next_lamp;

  always @(posedge clk or negedge rst_n) begin
    if (!rst_n) begin
      state <= INIT;
      lamp  <= 16'h0000;
    end else begin
      state <= next_state;
      lamp  <= next_lamp;
    end
  end

  always @(*) begin
    next_state = state;
    next_lamp  = lamp;
    case (state)

      // INIT: chờ flick
      INIT: begin
        next_lamp  = 16'h0000;
        if (flick)
          next_state = S1;
      end

      // Phase 1: ON L0→L5 (không check kickback)
      S1: begin
        if (lamp == 16'h0000)
          next_lamp = 16'h0001;
        else if (lamp == 16'h003F)
          next_state = S2;
        else
          next_lamp = lamp | (lamp << 1);
      end

      // Phase 2: OFF L5→L0
      S2: begin
        if (lamp == 16'h0001) begin
          next_lamp  = 16'h0000;
          next_state = S3;
        end else
          next_lamp = lamp >> 1;
      end

      // Phase 3: ON L0→L10 (kickback tại L5 và L10)
      S3: begin
        if (lamp == 16'h0000)
          next_lamp = 16'h0001;
        else if ((lamp == 16'h003F || lamp == 16'h07FF) && flick) begin
          next_lamp  = lamp;
          next_state = S3K;
        end else if (lamp == 16'h07FF)
          next_state = S4;
        else
          next_lamp = lamp | (lamp << 1);
      end

      // S3K: OFF về L0, quay lại S3
      S3K: begin
        if (lamp == 16'h0001) begin
          next_lamp  = 16'h0000;
          next_state = S3;
        end else
          next_lamp = lamp >> 1;
      end

      // Phase 4: OFF L10→L5
      S4: begin
        if (lamp == 16'h003F)
          next_state = S5;
        else
          next_lamp = lamp >> 1;
      end

      // Phase 5: ON L5→L15 (kickback tại L10)
      S5: begin
        if (lamp == 16'h07FF && flick) begin
          next_lamp  = lamp;
          next_state = S5K;
        end else if (lamp == 16'hFFFF)
          next_state = S6;
        else
          next_lamp = lamp | (lamp << 1);
      end

      // S5K: OFF về L5, quay lại S5
      S5K: begin
        if (lamp == 16'h003F) begin
          next_lamp  = lamp;
          next_state = S5;
        end else
          next_lamp = lamp >> 1;
      end

      // Phase 6: OFF L15→L0
      S6: begin
        if (lamp == 16'h0001) begin
          next_lamp  = 16'h0000;
          next_state = INIT;
        end else
          next_lamp = lamp >> 1;
      end

      default: begin
        next_state = INIT;
        next_lamp  = 16'h0000;
      end

    endcase
  end
endmodule

LAB1/bound_flasher_tb.v
`timescale 1ns/1ps
`define CYCLE 100
`include "bound_flasher.v"

module testbench;
  reg         clk;
  reg         rst_n;
  reg         flick;
  wire [15:0] lamp;

  bound_flasher bound_flasher_01 (
    .lamp  (lamp),
    .clk   (clk),
    .rst_n (rst_n),
    .flick (flick)
  );

  initial clk = 0;
  always #(`CYCLE/2) clk = ~clk;

  initial begin
    $dumpfile("waves.vcd");
    $dumpvars(0, testbench);
  end

  initial begin
    $monitor("time=%0d state=%0d flick=%b lamp=%h",
              $time, testbench.bound_flasher_01.state,
              flick, lamp);
  end

  initial begin

    //--------------------------------------------------
    // TEST CASE 1: flick=0 toàn bộ quá trình
    // Flow chuẩn không kickback:
    // INIT→S1(6)→S2(6)→S3(11)→S4(6)→S5(11)→S6(16)→INIT
    // Tổng ~56 cycles
    //--------------------------------------------------
    $display("========================================");
    $display("TEST CASE 1: flick=0 toan bo qua trinh");
    $display("========================================");
    rst_n = 0; flick = 0;
    #(`CYCLE*3);
    rst_n = 1;
    #(`CYCLE*2);
    flick = 1;       // trigger 1 cycle để vào S1
    #(`CYCLE*1);
    flick = 0;       // giữ flick=0 toàn bộ
    #(`CYCLE*100);   // đủ cho 1 chu kỳ đầy đủ

//--------------------------------------------------
// TEST CASE 2: kickback only at lamp[5] in S3
// Flow: INIT -> S1(6) -> S2(6) -> S3 up to lamp[5]
//       -> S3K (OFF back to lamp[0]) -> S3 restart
//       -> S4 -> S5 -> S6 -> INIT
//--------------------------------------------------
$display("========================================");
$display("TEST CASE 2: kickback at lamp[5] in S3");
$display("========================================");
rst_n = 0; flick = 0;
#(`CYCLE*3);          // Hold reset 3 cycles
rst_n = 1;
#(`CYCLE*2);          // Wait 2 cycles after reset
flick = 1;
#(`CYCLE*1);          // Pulse flick to start sequence
flick = 0;

// Wait until lamp[5] kickback point in S3:
// S1 = 6 cycles
// S2 = 6 cycles
// S3 from lamp[0] to lamp[5] = 6 cycles
// Total = 18 cycles
#(`CYCLE*18);
flick = 1;            // Assert flick at lamp[5] -> trigger kickback -> S3K
#(`CYCLE*3);          // Hold flick long enough to be sampled
flick = 0;

// Let the rest of sequence complete normally (no more kickback)
#(`CYCLE*150);

    //--------------------------------------------------
    // TEST CASE 3: flick=1 tại kickback L10
    //              khi đang đếm S3: L0→L10
    // Timing:
    //   S1(6) + S2(6) + S3 đến L10(11) = 23 cycles
    //--------------------------------------------------
    $display("========================================");
    $display("TEST CASE 3: flick=1 tai L10 trong S3 (L0->L10)");
    $display("========================================");
    rst_n = 0; flick = 0;
    #(`CYCLE*3);
    rst_n = 1;
    #(`CYCLE*2);
    flick = 1;       // trigger vào S1
    #(`CYCLE*1);
    flick = 0;
    // chờ qua S1(6) + S2(6) + S3 đến L10(11) = 23 cycles
    #(`CYCLE*23);
    flick = 1;       // assert tại L10 trong S3 → kickback về L0
    #(`CYCLE*2);
    flick = 0;
    #(`CYCLE*200);   // đủ để hoàn thành chu kỳ

    //--------------------------------------------------
    // TEST CASE 4: flick=1 tại kickback L10
    //              khi đang đếm S5: L5→L15
    // Timing:
    //   S1(6)+S2(6)+S3(11)+S4(6) = 29 cycles để vào S5
    //   S5 đến L10 = 6 cycles → tổng 35 cycles
    //--------------------------------------------------
    $display("========================================");
    $display("TEST CASE 4: flick=1 tai L10 trong S5 (L5->L15)");
    $display("========================================");
    rst_n = 0; flick = 0;
    #(`CYCLE*3);
    rst_n = 1;
    #(`CYCLE*2);
    flick = 1;       // trigger vào S1
    #(`CYCLE*1);
    flick = 0;
    // chờ qua S1(6)+S2(6)+S3(11)+S4(6)+S5 đến L10(6) = 35 cycles
    #(`CYCLE*35);
    flick = 1;       // assert tại L10 trong S5 → kickback về L5
    #(`CYCLE*2);
    flick = 0;
    #(`CYCLE*200);   // đủ để hoàn thành chu kỳ
    
    
        //--------------------------------------------------
    // TEST CASE 5: flick=1 tại CẢ L5 VÀ L10 trong S3
    // Kịch bản:
    //   - Đang bật L0→L10 (S3)
    //   - Gặp flick=1 tại L5 → kickback về L0 → bật lại
    //   - Lần này flick=0 tại L5 → tiếp tục lên L10
    //   - Gặp flick=1 tại L10 → kickback về L0 → bật lại
    //   - flick=0 tại L10 → sang S4 bình thường
    // Timing:
    //   S1(6)+S2(6) = 12 cycles để vào S3
    //   S3 đến L5   = 6 cycles  → tổng 18 cycles
    //   S3K tắt L5→L0 = 6 cycles
    //   S3 bật lại L0→L5 = 6 cycles → tổng 30 cycles
    //   S3 tiếp tục L5→L10 = 5 cycles → tổng 35 cycles
    //--------------------------------------------------
    $display("========================================");
    $display("TEST CASE 5: flick=1 tai ca L5 va L10 trong S3");
    $display("========================================");
    rst_n = 0; flick = 0;
    #(`CYCLE*3);
    rst_n = 1;
    #(`CYCLE*2);
    flick = 1;        // trigger vào S1
    #(`CYCLE*1);
    flick = 0;

    // chờ S1(6) + S2(6) + S3 đến L5(6) = 18 cycles
    #(`CYCLE*18);
    flick = 1;        // assert tại L5 → kickback lần 1
    #(`CYCLE*2);
    flick = 0;

    // S3K tắt L5→L0 (6 cycles) → S3 bật lại
    // S3 bật L0→L5 (6 cycles) → flick=0 tại L5, tiếp tục
    // S3 bật L5→L10 (5 cycles)
    // tổng chờ: 6 + 6 + 5 = 17 cycles
    #(`CYCLE*17);
    flick = 1;        // assert tại L10 → kickback lần 2
    #(`CYCLE*2);
    flick = 0;

    // S3K tắt L10→L0 → S3 bật lại L0→L10 → flick=0 → sang S4
    #(`CYCLE*250);    // đủ để hoàn thành chu kỳ
    
    
    //--------------------------------------------------
    // TEST CASE 6: flick=1 tại CẢ 3 kickback points
    // Kịch bản:
    //   - S3: gặp flick=1 tại L5  → kickback về L0
    //   - S3: gặp flick=1 tại L10 → kickback về L0
    //   - S5: gặp flick=1 tại L10 → kickback về L5
    // Timing:
    //   S1(6)+S2(6) = 12 cycles để vào S3
    //   S3 đến L5   = 6 cycles  → tổng 18 cycles
    //   --- kickback 1: S3K(6) + S3 đến L10(11) = 17 cycles
    //   → tổng 35 cycles tới L10 trong S3
    //   --- kickback 2: S3K(6) + S3(11) + S4(6) + S5 đến L10(6) 
    //   = 29 cycles
    //   → tổng 64 cycles tới L10 trong S5
    //--------------------------------------------------
    $display("========================================");
    $display("TEST CASE 6: flick=1 tai ca 3 kickback points");
    $display("========================================");
    rst_n = 0; flick = 0;
    #(`CYCLE*3);
    rst_n = 1;
    #(`CYCLE*2);
    flick = 1;        // trigger vào S1
    #(`CYCLE*1);
    flick = 0;

    // ── Kickback 1: L5 trong S3 ──────────────────────
    // chờ S1(6) + S2(6) + S3 đến L5(6) = 18 cycles
    #(`CYCLE*18);
    flick = 1;        // assert tại L5 → kickback về L0
    #(`CYCLE*2);
    flick = 0;

    // ── Kickback 2: L10 trong S3 ─────────────────────
    // S3K tắt L5→L0 (6) + S3 bật L0→L10 (11) = 17 cycles
    #(`CYCLE*17);
    flick = 1;        // assert tại L10 → kickback về L0
    #(`CYCLE*2);
    flick = 0;

    // ── Kickback 3: L10 trong S5 ─────────────────────
    // S3K tắt L10→L0 (10) + S3 bật L0→L10 (11)
    // + S4 tắt L10→L5 (6) + S5 bật L5→L10 (6) = 33 cycles
    #(`CYCLE*33);
    flick = 1;        // assert tại L10 trong S5 → kickback về L5
    #(`CYCLE*2);
    flick = 0;

    // S5K tắt L10→L5 → S5 tiếp tục bật L5→L15 → S6 → INIT
    #(`CYCLE*300);    // đủ để hoàn thành chu kỳ
    

    $display("========================================");
    $display("SIMULATION DONE");
    $display("========================================");
    $finish;
  end

endmodule

LAB1/waves.vcd
$date
	Wed Apr 01 17:21:54 2026
$end
$version
	Icarus Verilog
$end
$timescale
	1ps
$end
$scope module testbench $end
$var wire 16 ! lamp [15:0] $end
$var reg 1 " clk $end
$var reg 1 # flick $end
$var reg 1 $ rst_n $end
$scope module bound_flasher_01 $end
$var wire 1 " clk $end
$var wire 1 # flick $end
$var wire 1 $ rst_n $end
$var reg 16 % lamp [15:0] $end
$var reg 16 & next_lamp [15:0] $end
$var reg 4 ' next_state [3:0] $end
$var reg 4 ( state [3:0] $end
$upscope $end
$upscope $end
$enddefinitions $end
#0
$dumpvars
b0 (
b0 '
b0 &
b0 %
0$
0#
0"
b0 !
$end
#50000
1"
#100000
0"
#150000
1"
#200000
0"
#250000
1"
#300000
0"
1$
#350000
1"
#400000
0"
#450000
1"
#500000
b1 '
0"
1#
#550000
b1 &
b1 (
1"
#600000
b1 &
0"
0#
#650000
b11 &
b1 !
b1 %
1"
#700000
0"
#750000
b111 &
b11 !
b11 %
1"
#800000
0"
#850000
b1111 &
b111 !
b111 %
1"
#900000
0"
#950000
b11111 &
b1111 !
b1111 %
1"
#1000000
0"
#1050000
b111111 &
b11111 !
b11111 %
1"
#1100000
0"
#1150000
b10 '
b111111 !
b111111 %
1"
#1200000
0"
#1250000
b11111 &
b10 (
1"
#1300000
0"
#1350000
b1111 &
b11111 !
b11111 %
1"
#1400000
0"
#1450000
b111 &
b1111 !
b1111 %
1"
#1500000
0"
#1550000
b11 &
b111 !
b111 %
1"
#1600000
0"
#1650000
b1 &
b11 !
b11 %
1"
#1700000
0"
#1750000
b11 '
b0 &
b1 !
b1 %
1"
#1800000
0"
#1850000
b1 &
b0 !
b0 %
b11 (
1"
#1900000
0"
#1950000
b11 &
b1 !
b1 %
1"
#2000000
0"
#2050000
b111 &
b11 !
b11 %
1"
#2100000
0"
#2150000
b1111 &
b111 !
b111 %
1"
#2200000
0"
#2250000
b11111 &
b1111 !
b1111 %
1"
#2300000
0"
#2350000
b111111 &
b11111 !
b11111 %
1"
#2400000
0"
#2450000
b1111111 &
b111111 !
b111111 %
1"
#2500000
0"
#2550000
b11111111 &
b1111111 !
b1111111 %
1"
#2600000
0"
#2650000
b111111111 &
b11111111 !
b11111111 %
1"
#2700000
0"
#2750000
b1111111111 &
b111111111 !
b111111111 %
1"
#2800000
0"
#2850000
b11111111111 &
b1111111111 !
b1111111111 %
1"
#2900000
0"
#2950000
b101 '
b11111111111 !
b11111111111 %
1"
#3000000
0"
#3050000
b1111111111 &
b101 (
1"
#3100000
0"
#3150000
b111111111 &
b1111111111 !
b1111111111 %
1"
#3200000
0"
#3250000
b11111111 &
b111111111 !
b111111111 %
1"
#3300000
0"
#3350000
b1111111 &
b11111111 !
b11111111 %
1"
#3400000
0"
#3450000
b111111 &
b1111111 !
b1111111 %
1"
#3500000
0"
#3550000
b110 '
b111111 !
b111111 %
1"
#3600000
0"
#3650000
b1111111 &
b110 (
1"
#3700000
0"
#3750000
b11111111 &
b1111111 !
b1111111 %
1"
#3800000
0"
#3850000
b111111111 &
b11111111 !
b11111111 %
1"
#3900000
0"
#3950000
b1111111111 &
b111111111 !
b111111111 %
1"
#4000000
0"
#4050000
b11111111111 &
b1111111111 !
b1111111111 %
1"
#4100000
0"
#4150000
b111111111111 &
b11111111111 !
b11111111111 %
1"
#4200000
0"
#4250000
b1111111111111 &
b111111111111 !
b111111111111 %
1"
#4300000
0"
#4350000
b11111111111111 &
b1111111111111 !
b1111111111111 %
1"
#4400000
0"
#4450000
b111111111111111 &
b11111111111111 !
b11111111111111 %
1"
#4500000
0"
#4550000
b1111111111111111 &
b111111111111111 !
b111111111111111 %
1"
#4600000
0"
#4650000
b1000 '
b1111111111111111 !
b1111111111111111 %
1"
#4700000
0"
#4750000
b111111111111111 &
b1000 (
1"
#4800000
0"
#4850000
b11111111111111 &
b111111111111111 !
b111111111111111 %
1"
#4900000
0"
#4950000
b1111111111111 &
b11111111111111 !
b11111111111111 %
1"
#5000000
0"
#5050000
b111111111111 &
b1111111111111 !
b1111111111111 %
1"
#5100000
0"
#5150000
b11111111111 &
b111111111111 !
b111111111111 %
1"
#5200000
0"
#5250000
b1111111111 &
b11111111111 !
b11111111111 %
1"
#5300000
0"
#5350000
b111111111 &
b1111111111 !
b1111111111 %
1"
#5400000
0"
#5450000
b11111111 &
b111111111 !
b111111111 %
1"
#5500000
0"
#5550000
b1111111 &
b11111111 !
b11111111 %
1"
#5600000
0"
#5650000
b111111 &
b1111111 !
b1111111 %
1"
#5700000
0"
#5750000
b11111 &
b111111 !
b111111 %
1"
#5800000
0"
#5850000
b1111 &
b11111 !
b11111 %
1"
#5900000
0"
#5950000
b111 &
b1111 !
b1111 %
1"
#6000000
0"
#6050000
b11 &
b111 !
b111 %
1"
#6100000
0"
#6150000
b1 &
b11 !
b11 %
1"
#6200000
0"
#6250000
b0 '
b0 &
b1 !
b1 %
1"
#6300000
0"
#6350000
b0 !
b0 %
b0 (
1"
